ovos_persona_server/__init__.py
ovos_persona_server/__main__.py
ovos_persona_server/chat.py
ovos_persona_server/ollama.py
ovos_persona_server/persona.py
ovos_persona_server/version.py
ovos_persona_server-0.5.0.dist-info/licenses/LICENSE
ovos_persona_server-0.5.0.dist-info/METADATA
ovos_persona_server-0.5.0.dist-info/WHEEL
ovos_persona_server-0.5.0.dist-info/entry_points.txt
ovos_persona_server-0.5.0.dist-info/top_level.txt
ovos_persona_server-0.5.0.dist-info/zip-safe
ovos_persona_server-0.5.0.dist-info/RECORD
