Metadata-Version: 2.4
Name: ovos-persona-server
Version: 0.5.0
Summary: simple flask server to host OpenVoiceOS persona plugins as a service
Home-page: https://github.com/OpenVoiceOS/ovos-persona-server
Author: JarbasAi
Author-email: jarbasai@mailfence.com
License: Apache-2.0
Keywords: plugin lang detect translate OVOS OpenVoiceOS
Classifier: Development Status :: 3 - Alpha
Classifier: Intended Audience :: Developers
Classifier: Topic :: Text Processing :: Linguistic
Classifier: License :: OSI Approved :: Apache Software License
Classifier: Programming Language :: Python :: 3.6
Classifier: Programming Language :: Python :: 3.7
Classifier: Programming Language :: Python :: 3.8
Classifier: Programming Language :: Python :: 3.9
Classifier: Programming Language :: Python :: 3.10
Classifier: Programming Language :: Python :: 3.11
License-File: LICENSE
Requires-Dist: fastapi
Requires-Dist: ovos-persona
Requires-Dist: pydantic
Dynamic: author
Dynamic: author-email
Dynamic: classifier
Dynamic: description
Dynamic: description-content-type
Dynamic: home-page
Dynamic: keywords
Dynamic: license
Dynamic: license-file
Dynamic: requires-dist
Dynamic: summary
